{"chunk_definitions":[{"row":20,"row_count":1,"visible":true,"expansion_state":0,"options":{"engine":"r","include":false,"label":"unnamed-chunk-1"},"document_id":"04FE9605","chunk_id":"ck4acbm5pw7ft","chunk_label":"unnamed-chunk-1"},{"row":119,"row_count":1,"visible":true,"expansion_state":0,"options":{"engine":"r","include":false,"label":"unnamed-chunk-2"},"document_id":"04FE9605","chunk_id":"c74p0wq2x8x2e","chunk_label":"unnamed-chunk-2"},{"row":131,"row_count":1,"visible":true,"expansion_state":0,"options":{"engine":"r","include":false,"label":"unnamed-chunk-3"},"document_id":"04FE9605","chunk_id":"c03qykaspqqj8","chunk_label":"unnamed-chunk-3"},{"row":194,"row_count":1,"visible":true,"expansion_state":0,"options":{"engine":"r","echo":false,"message":false,"warning":false,"paged.print":false,"label":"unnamed-chunk-4"},"document_id":"04FE9605","chunk_id":"c6a1lucww8h8g","chunk_label":"unnamed-chunk-9"}],"doc_write_time":1731308029}