{"chunk_definitions":[{"row":15,"row_count":1,"visible":true,"expansion_state":0,"options":{"engine":"r","label":"setup","include":false},"document_id":"E4ABAE00","chunk_id":"csetup_chunk","chunk_label":"setup"},{"row":23,"row_count":1,"visible":true,"expansion_state":0,"options":{"engine":"r","label":"unnamed-chunk-1"},"document_id":"E4ABAE00","chunk_id":"c1pbt8k9wnz4h","chunk_label":"unnamed-chunk-1"},{"row":45,"row_count":1,"visible":true,"expansion_state":0,"options":{"engine":"r","label":"unnamed-chunk-92"},"document_id":"E4ABAE00","chunk_id":"cex6s3ee6k3v5","chunk_label":"unnamed-chunk-2"},{"row":56,"row_count":1,"visible":true,"expansion_state":0,"options":{"engine":"r","label":"unnamed-chunk-29"},"document_id":"E4ABAE00","chunk_id":"cny0hcxy4to2b","chunk_label":"unnamed-chunk-3"}],"doc_write_time":0,"working_dir":null,"default_chunk_options":{"echo":true},"chunk_rendered_width":684}